{"cameraMode":{"drawMode":0,"name":"Shaded","section":"Shading Mode"},"sceneLighting":true,"audioPlay":false,"sceneViewState":{"m_AlwaysRefresh":false,"showFog":true,"showSkybox":true,"showFlares":true,"showImageEffects":true,"showParticleSystems":true,"showVisualEffectGraphs":true,"m_FxEnabled":true},"in2DMode":false,"pivot":{"x":24.84735679626465,"y":-15.273133277893067,"z":13.52192211151123},"rotation":{"x":-0.22129105031490327,"y":-0.505897045135498,"z":0.13610269129276277,"w":-0.8225468993186951},"size":20.101091384887697,"orthographic":false}